pyravia/__init__.py
pyravia/tv.py
pyravia/tests/__init__.py
pyravia/tests/base.py
pyravia/tests/test_pyravia.py
pyravia-0.0.3.dist-info/DESCRIPTION.rst
pyravia-0.0.3.dist-info/METADATA
pyravia-0.0.3.dist-info/RECORD
pyravia-0.0.3.dist-info/WHEEL
pyravia-0.0.3.dist-info/metadata.json
pyravia-0.0.3.dist-info/pbr.json
pyravia-0.0.3.dist-info/top_level.txt
