Metadata-Version: 2.0
Name: pyravia
Version: 0.0.3
Summary: Library to control Sony TVs and Stereos
Home-page: http://inaugust.com
Author: Monty Taylor
Author-email: mordred@inaugust.com
License: UNKNOWN
Platform: UNKNOWN
Classifier: Intended Audience :: Information Technology
Classifier: Intended Audience :: System Administrators
Classifier: License :: OSI Approved :: GNU General Public License v3 or later (GPLv3+)
Classifier: Operating System :: POSIX :: Linux
Classifier: Programming Language :: Python
Classifier: Programming Language :: Python :: 2
Classifier: Programming Language :: Python :: 2.7
Classifier: Programming Language :: Python :: 3
Classifier: Programming Language :: Python :: 3.3
Classifier: Programming Language :: Python :: 3.5
Requires-Dist: pbr (>=1.8)
Requires-Dist: requests
